lsfm_fuse/NSCT.py
lsfm_fuse/__init__.py
lsfm_fuse/blobs_dog.py
lsfm_fuse/fuse_det.py
lsfm_fuse/fuse_illu.py
lsfm_fuse/utils.py
lsfm_fuse/bin/__init__.py
lsfm_fuse/bin/run_fuse_det.py
lsfm_fuse/bin/run_fuse_illu.py
lsfm_fuse-0.1.2.dist-info/LICENSE
lsfm_fuse-0.1.2.dist-info/METADATA
lsfm_fuse-0.1.2.dist-info/WHEEL
lsfm_fuse-0.1.2.dist-info/entry_points.txt
lsfm_fuse-0.1.2.dist-info/top_level.txt
lsfm_fuse-0.1.2.dist-info/RECORD
