Metadata-Version: 2.1
Name: lsfm-fuse
Version: 0.1.2
Summary: A fusion algorithm in LSFM
Home-page: https://github.com/peng-lab/lsfm_fuse
Author: Yu Liu
Author-email: liuyu9671@gmail.com
License: MIT license
Keywords: lsfm_fuse
Platform: UNKNOWN
Classifier: Development Status :: 2 - Pre-Alpha
Classifier: Intended Audience :: Developers
Classifier: License :: OSI Approved :: MIT License
Classifier: Natural Language :: English
Classifier: Programming Language :: Python :: 3.9
Classifier: Programming Language :: Python :: 3.10
Classifier: Programming Language :: Python :: 3.11
Requires-Python: >=3.9
License-File: LICENSE
Requires-Dist: scikit-image
Requires-Dist: torch
Requires-Dist: torchvision
Requires-Dist: tqdm
Requires-Dist: aicsimageio
Requires-Dist: antspyx
Requires-Dist: SimpleITK
Requires-Dist: opencv-python
Requires-Dist: colour
Requires-Dist: open3d
Requires-Dist: h5py
Provides-Extra: all
Requires-Dist: scikit-image; extra == "all"
Requires-Dist: torch; extra == "all"
Requires-Dist: torchvision; extra == "all"
Requires-Dist: tqdm; extra == "all"
Requires-Dist: aicsimageio; extra == "all"
Requires-Dist: antspyx; extra == "all"
Requires-Dist: SimpleITK; extra == "all"
Requires-Dist: opencv-python; extra == "all"
Requires-Dist: colour; extra == "all"
Requires-Dist: open3d; extra == "all"
Requires-Dist: h5py; extra == "all"
Requires-Dist: pytest-runner>=5.2; extra == "all"
Requires-Dist: black>=19.10b0; extra == "all"
Requires-Dist: codecov>=2.1.4; extra == "all"
Requires-Dist: flake8>=3.8.3; extra == "all"
Requires-Dist: flake8-debugger>=3.2.1; extra == "all"
Requires-Dist: pytest>=5.4.3; extra == "all"
Requires-Dist: pytest-cov>=2.9.0; extra == "all"
Requires-Dist: pytest-raises>=0.11; extra == "all"
Requires-Dist: bump2version>=1.0.1; extra == "all"
Requires-Dist: coverage>=5.1; extra == "all"
Requires-Dist: ipython>=7.15.0; extra == "all"
Requires-Dist: m2r2>=0.2.7; extra == "all"
Requires-Dist: Sphinx>=3.4.3; extra == "all"
Requires-Dist: sphinx-rtd-theme>=0.5.1; extra == "all"
Requires-Dist: tox>=3.15.2; extra == "all"
Requires-Dist: twine>=3.1.1; extra == "all"
Requires-Dist: wheel>=0.34.2; extra == "all"
Provides-Extra: dev
Requires-Dist: pytest-runner>=5.2; extra == "dev"
Requires-Dist: black>=19.10b0; extra == "dev"
Requires-Dist: codecov>=2.1.4; extra == "dev"
Requires-Dist: flake8>=3.8.3; extra == "dev"
Requires-Dist: flake8-debugger>=3.2.1; extra == "dev"
Requires-Dist: pytest>=5.4.3; extra == "dev"
Requires-Dist: pytest-cov>=2.9.0; extra == "dev"
Requires-Dist: pytest-raises>=0.11; extra == "dev"
Requires-Dist: bump2version>=1.0.1; extra == "dev"
Requires-Dist: coverage>=5.1; extra == "dev"
Requires-Dist: ipython>=7.15.0; extra == "dev"
Requires-Dist: m2r2>=0.2.7; extra == "dev"
Requires-Dist: Sphinx>=3.4.3; extra == "dev"
Requires-Dist: sphinx-rtd-theme>=0.5.1; extra == "dev"
Requires-Dist: tox>=3.15.2; extra == "dev"
Requires-Dist: twine>=3.1.1; extra == "dev"
Requires-Dist: wheel>=0.34.2; extra == "dev"
Provides-Extra: setup
Requires-Dist: pytest-runner>=5.2; extra == "setup"
Provides-Extra: test
Requires-Dist: black>=19.10b0; extra == "test"
Requires-Dist: codecov>=2.1.4; extra == "test"
Requires-Dist: flake8>=3.8.3; extra == "test"
Requires-Dist: flake8-debugger>=3.2.1; extra == "test"
Requires-Dist: pytest>=5.4.3; extra == "test"
Requires-Dist: pytest-cov>=2.9.0; extra == "test"
Requires-Dist: pytest-raises>=0.11; extra == "test"
